quovo/__init__.py
quovo-100.100.100.dist-info/LICENSE
quovo-100.100.100.dist-info/METADATA
quovo-100.100.100.dist-info/WHEEL
quovo-100.100.100.dist-info/top_level.txt
quovo-100.100.100.dist-info/RECORD
