Metadata-Version: 2.1
Name: quovo
Version: 100.100.100
Summary: For questions reach out to security@plaid.com
Home-page: https://www.plaid.com
Author: Plaid
Author-email: agupta@plaid.com
License: BSD 2-clause
Platform: UNKNOWN
